forger/__init__.py
forger/forger.py
forger/utils.py
forger-0.0.0.dist-info/AUTHORS.rst
forger-0.0.0.dist-info/LICENSE
forger-0.0.0.dist-info/METADATA
forger-0.0.0.dist-info/WHEEL
forger-0.0.0.dist-info/top_level.txt
forger-0.0.0.dist-info/RECORD
