Metadata-Version: 2.1
Name: forger
Version: 0.0.0
Summary: A package for 3D image augmentation
Home-page: https://github.com/FarhadMaleki/forger
Author: Farhad Maleki
Author-email: farhad.maleki@mail.mcgill.ca
License: LGPL-3.0-only
Project-URL: Documentation, https://forger.readthedocs.io/
Project-URL: Changelog, https://forger.readthedocs.io/en/latest/changelog.html
Project-URL: Issue Tracker, https://github.com/FarhadMaleki/forger/issues
Keywords: data augmentation,3D image,medical imaging
Platform: UNKNOWN
Classifier: Development Status :: 4 - Beta
Classifier: Intended Audience :: Developers
Classifier: Intended Audience :: Science/Research
Classifier: Topic :: Scientific/Engineering
Classifier: Topic :: Scientific/Engineering :: Image Processing
Classifier: License :: OSI Approved :: GNU Lesser General Public License v3 (LGPLv3)
Classifier: Operating System :: Unix
Classifier: Operating System :: POSIX
Classifier: Operating System :: Microsoft :: Windows
Classifier: Programming Language :: Python
Classifier: Programming Language :: Python :: 3
Classifier: Programming Language :: Python :: 3 :: Only
Classifier: Programming Language :: Python :: 3.6
Classifier: Programming Language :: Python :: 3.7
Classifier: Programming Language :: Python :: 3.8
Classifier: Programming Language :: Python :: 3.9
Classifier: Programming Language :: Python :: Implementation :: CPython
Classifier: Programming Language :: Python :: Implementation :: PyPy
Classifier: Topic :: Utilities
Requires-Python: >=3.6
License-File: LICENSE
License-File: AUTHORS.rst
Requires-Dist: aspectlib (>=1.1.1)
Requires-Dist: SimpleITK (>=2.0.2)
